[
    {
        "fuente": "Wired en Español",
        "titulo": "Corea del Norte ha creado una unidad de hackers dedicada a la inteligencia artificial",
        "enlace": "https://es.wired.com/articulos/corea-del-norte-ha-creado-una-unidad-de-hackers-dedicada-a-la-inteligencia-artificial",
        "resumen": "Corea del Norte refuerza su apuesta por los proyectos de hackeo informático dirigidos al mundo occidental.\nDe acuerdo con la fuente, la orden de Jong Un contemplaba que el Centro de Investigación 227 se estableciera en su totalidad el 9 de marzo.\nMientras las oficinas del RGB se localizan en el distrito Pyongyang Hyongjesan, el Centro de Investigación 227 está situado en el distrito Mangyongdae\", comenta la fuente a Daily NK.\nAdemás, para que la unidad sea aún más funcional, las autoridades prevén que el centro opere las 24 horas del día, de modo que pueda procesar en tiempo real la información que llega de los piratas informáticos norcoreanos situados fuera de las fronteras del país.\nLa RGB ya está reclutando al personal que trabajará en el Centro de Investigación 227, con la intención de contratar a un total de 90 expertos informáticos, egresados con excelentes calificaciones.",
        "fecha_publicacion": "2025-03-21T20:32:27.179000+00:00",
        "fecha_actualizacion": "2025-03-23T00:49:41.533578"
    }
]